FDApy/__init__.py
FDApy/py.typed
FDApy/misc/__init__.py
FDApy/misc/basis.py
FDApy/misc/loader.py
FDApy/misc/utils.py
FDApy/preprocessing/__init__.py
FDApy/preprocessing/dim_reduction/__init__.py
FDApy/preprocessing/dim_reduction/fcp_tpa.py
FDApy/preprocessing/dim_reduction/mfpca.py
FDApy/preprocessing/dim_reduction/ufpca.py
FDApy/preprocessing/smoothing/__init__.py
FDApy/preprocessing/smoothing/local_polynomial.py
FDApy/preprocessing/smoothing/psplines.py
FDApy/representation/__init__.py
FDApy/representation/argvals.py
FDApy/representation/basis.py
FDApy/representation/functional_data.py
FDApy/representation/values.py
FDApy/simulation/__init__.py
FDApy/simulation/brownian.py
FDApy/simulation/datasets.py
FDApy/simulation/karhunen.py
FDApy/simulation/simulation.py
FDApy/visualization/__init__.py
FDApy/visualization/_plot.py
fdapy-1.0.3.dist-info/LICENSE
fdapy-1.0.3.dist-info/METADATA
fdapy-1.0.3.dist-info/WHEEL
fdapy-1.0.3.dist-info/top_level.txt
fdapy-1.0.3.dist-info/RECORD
