Metadata-Version: 2.2
Name: FDApy
Version: 1.0.3
Summary: A Python package to analyze functional data.
Maintainer-email: Steven Golovkine <steven_golovkine@icloud.com>
License: MIT License
Project-URL: homepage, https://github.com/StevenGolovkine/FDApy
Project-URL: documentation, https://fdapy.readthedocs.io
Project-URL: repository, https://github.com/StevenGolovkine/FDApy
Keywords: functional data analysis
Classifier: Programming Language :: Python :: 3.10
Classifier: Topic :: Scientific/Engineering :: Mathematics
Requires-Python: <4,>=3.10
License-File: LICENSE
Requires-Dist: lazy_loader
Requires-Dist: matplotlib
Requires-Dist: numpy<2.0.0
Requires-Dist: pandas>=2.0.0
Requires-Dist: scikit-learn>=1.2.0
Requires-Dist: scipy>=1.10.0
Provides-Extra: docs
Requires-Dist: matplotlib; extra == "docs"
Requires-Dist: mpldatacursor; extra == "docs"
Requires-Dist: numpydoc; extra == "docs"
Requires-Dist: numpy<2.0.0; extra == "docs"
Requires-Dist: pandas>=2.0.0; extra == "docs"
Requires-Dist: pillow; extra == "docs"
Requires-Dist: pydata-sphinx-theme==0.16.0; extra == "docs"
Requires-Dist: scikit-learn; extra == "docs"
Requires-Dist: scikit-fda; extra == "docs"
Requires-Dist: scipy; extra == "docs"
Requires-Dist: setuptools>=41.2; extra == "docs"
Requires-Dist: sphinx>=3; extra == "docs"
Requires-Dist: sphinxcontrib-bibtex; extra == "docs"
Requires-Dist: sphinx-gallery; extra == "docs"
Provides-Extra: test
Requires-Dist: pytest; extra == "test"
Requires-Dist: pytest-env; extra == "test"
Requires-Dist: pytest-subtests; extra == "test"
Requires-Dist: scipy; extra == "test"
